pdunehd/__init__.py
pdunehd-1.3.1.dist-info/LICENSE
pdunehd-1.3.1.dist-info/METADATA
pdunehd-1.3.1.dist-info/WHEEL
pdunehd-1.3.1.dist-info/top_level.txt
pdunehd-1.3.1.dist-info/RECORD
