Metadata-Version: 2.1
Name: pdunehd
Version: 1.3.1
Summary: A Python wrapper for Dune HD media player API
Home-page: https://github.com/valentinalexeev/pdunehd
Author: Valentin Alexeev
Author-email: valentin.alekseev@gmail.com
License: UNKNOWN
Platform: UNKNOWN
Classifier: Programming Language :: Python :: 3
Classifier: License :: OSI Approved :: Apache Software License
Classifier: Operating System :: OS Independent
Requires-Python: >=3.6
